confluence_utils/__init__.py
confluence_utils/confluence_api.py
confluence_utils/i18n.py
gitlab_utils/__init__.py
gitlab_utils/gitlab_api.py
google_utils/__init__.py
google_utils/gmail_api.py
html_utils/__init__.py
html_utils/html_publisher.py
image_utils/__init__.py
image_utils/image_converter.py
open_ai_utils/__init__.py
open_ai_utils/translation.py
qr_utils/__init__.py
qr_utils/qr_code_generator.py
selenium_utils/__init__.py
selenium_utils/crawler.py
selenium_utils/lotto.py
tests/__init__.py
tests/conftest.py
python_rpa-0.0.4.dist-info/METADATA
python_rpa-0.0.4.dist-info/WHEEL
python_rpa-0.0.4.dist-info/top_level.txt
python_rpa-0.0.4.dist-info/RECORD
