Metadata-Version: 2.4
Name: python-rpa
Version: 0.0.4
Summary: A description of your package
Home-page: https://gitlab.hmg-corp.io/swdc/python-rpa
Author: Shinyoung Kim
Author-email: shinyoung.kim@hyundai-autoever.com
Requires-Python: >=3.9
Dynamic: author
Dynamic: author-email
Dynamic: description
Dynamic: description-content-type
Dynamic: home-page
Dynamic: requires-python
Dynamic: summary
